[{"name":"Adidas 45 tendance 2024","price":"23000.00","brand":"Adidas","items_left":"5","gender":"M","slug":"Merci bonne truc","is_in_inventory":"on","imageURL":"uploads\\image-1702672426109.jpg"},{"name":"Adidas","price":"30000.00","brand":"Adidas","items_left":"2","gender":"F","slug":"Merci","is_in_inventory":"on","imageURL":"uploads\\image-1702672574695.jpg"},{"name":"Adidas","price":"50000.00","brand":"Adidas","items_left":"14","gender":"M/F","slug":"m","is_in_inventory":"on","imageURL":"uploads\\image-1702672829507.png"},{"name":"Aiir Force ","price":"45000.00","brand":"Aiir Force ","items_left":"2","gender":"M","slug":"Blue","reduction":"13","is_in_inventory":"on","prix_initial":"39150","imageURL":"uploads\\image-1702673469050.jpg"},{"name":"Adidas","price":"13000","brand":"Adidas","items_left":"1","gender":"F","slug":"Love","reduction":"3","is_in_inventory":"on","prix_initial":"12610","imageURL":"uploads\\image-1702673702118.jpg"},{"name":"AIr Force","price":"45000.00","brand":"AIr Force","items_left":"2","gender":"M","slug":"Love","reduction":"10","is_in_inventory":"on","prix_initial":"40500","imageURL":"uploads\\image-1702673921756.jpg"},{"name":"Adidas","price":"45000.00","brand":"Adidas","items_left":"5","gender":"M/F","slug":"love","reduction":"20","is_in_inventory":"on","prix_initial":"36000","imageURL":"uploads\\image-1702674040671.jpg"},{"name":"Chanel","price":"50000.00","brand":"50000","items_left":"5","gender":"M/F","slug":"Solde","reduction":"40","is_in_inventory":"on","prix_initial":"30000","imageURL":"uploads\\image-1702674177976.jpg"},{"id":1702682941639,"name":"Nike, Priroda, Aviation. Utilisation gratuite","price":"12000.00","brand":"Nike","items_left":"2","gender":"M","slug":"love","reduction":"5","is_in_inventory":"on","prix_initial":"11400","imageURL":"uploads\\image-1702682941622.jpg"}]